tycho/__init__.py
tycho/app.py
tycho/main.py
tycho/db/__init__.py
tycho/db/connection.py
tycho/db/utils.py
tycho/db/event/__init__.py
tycho/db/event/deserialize.py
tycho/db/event/serialize.py
tycho/docs/design.html
tycho/docs/events.html
tycho/docs/genindex.html
tycho/docs/index.html
tycho/docs/objects.inv
tycho/docs/runbook.html
tycho/docs/search.html
tycho/docs/searchindex.js
tycho/docs/userguide.html
tycho/docs/.doctrees/design.doctree
tycho/docs/.doctrees/environment.pickle
tycho/docs/.doctrees/events.doctree
tycho/docs/.doctrees/index.doctree
tycho/docs/.doctrees/runbook.doctree
tycho/docs/.doctrees/userguide.doctree
tycho/docs/_sources/design.rst.txt
tycho/docs/_sources/events.rst.txt
tycho/docs/_sources/index.rst.txt
tycho/docs/_sources/runbook.rst.txt
tycho/docs/_sources/userguide.rst.txt
tycho/docs/_static/basic.css
tycho/docs/_static/doctools.js
tycho/docs/_static/documentation_options.js
tycho/docs/_static/file.png
tycho/docs/_static/jquery-3.5.1.js
tycho/docs/_static/jquery.js
tycho/docs/_static/language_data.js
tycho/docs/_static/minus.png
tycho/docs/_static/plus.png
tycho/docs/_static/pygments.css
tycho/docs/_static/searchtools.js
tycho/docs/_static/underscore-1.12.0.js
tycho/docs/_static/underscore.js
tycho/docs/_static/css/badge_only.css
tycho/docs/_static/css/theme.css
tycho/docs/_static/css/fonts/Roboto-Slab-Bold.woff
tycho/docs/_static/css/fonts/Roboto-Slab-Bold.woff2
tycho/docs/_static/css/fonts/Roboto-Slab-Regular.woff
tycho/docs/_static/css/fonts/Roboto-Slab-Regular.woff2
tycho/docs/_static/css/fonts/fontawesome-webfont.eot
tycho/docs/_static/css/fonts/fontawesome-webfont.svg
tycho/docs/_static/css/fonts/fontawesome-webfont.ttf
tycho/docs/_static/css/fonts/fontawesome-webfont.woff
tycho/docs/_static/css/fonts/fontawesome-webfont.woff2
tycho/docs/_static/css/fonts/lato-bold-italic.woff
tycho/docs/_static/css/fonts/lato-bold-italic.woff2
tycho/docs/_static/css/fonts/lato-bold.woff
tycho/docs/_static/css/fonts/lato-bold.woff2
tycho-0.5.1.dist-info/LICENSE
tycho-0.5.1.dist-info/METADATA
tycho-0.5.1.dist-info/WHEEL
tycho-0.5.1.dist-info/entry_points.txt
tycho-0.5.1.dist-info/top_level.txt
tycho-0.5.1.dist-info/RECORD
