Metadata-Version: 2.1
Name: tycho
Version: 0.5.1
Summary: UNKNOWN
Home-page: UNKNOWN
Author: zillow-orbital
Author-email: UNKNOWN
License: UNKNOWN
Platform: UNKNOWN
Requires-Dist: aiohttp
Requires-Dist: aiohttp-cors
Requires-Dist: aiohttp-transmute
Requires-Dist: motor
Requires-Dist: pymongo
Requires-Dist: orbital-core
